bayonet/__init__.py
bayonet/bayonet.py
bayonet/bayonet_base.py
bayonet/exceptions.py
bayonet/response.py
bayonetpython-0.0.0.dist-info/DESCRIPTION.rst
bayonetpython-0.0.0.dist-info/METADATA
bayonetpython-0.0.0.dist-info/RECORD
bayonetpython-0.0.0.dist-info/WHEEL
bayonetpython-0.0.0.dist-info/metadata.json
bayonetpython-0.0.0.dist-info/top_level.txt
test/test_bayonet.py
